dlight_client-1.2.0.dist-info/licenses/LICENSE
dlightclient/__init__.py
dlightclient/cli.py
dlightclient/client.py
dlightclient/constants.py
dlightclient/device.py
dlightclient/discovery.py
dlightclient/exceptions.py
dlight_client-1.2.0.dist-info/METADATA
dlight_client-1.2.0.dist-info/WHEEL
dlight_client-1.2.0.dist-info/top_level.txt
dlight_client-1.2.0.dist-info/RECORD
