Metadata-Version: 2.4
Name: dlight-client
Version: 1.2.0
Summary: A Python client for the dLight smart lamp API.
Author-email: David Kernan <dave@paddez.com>
License: Creative Commons Legal Code
Project-URL: Homepage, https://github.com/irishsmurf/dlight-client
Project-URL: Bug Tracker, https://github.com/irishsmurf/dlight-client/issues
Keywords: dlight,smart home,lighting,api,iot
Classifier: Programming Language :: Python :: 3
Classifier: License :: OSI Approved :: MIT License
Classifier: Operating System :: OS Independent
Classifier: Intended Audience :: Developers
Classifier: Topic :: Home Automation
Classifier: Topic :: System :: Networking
Requires-Python: >=3.7
License-File: LICENSE
Dynamic: license-file
